ruterstop/__init__.py
ruterstop/__main__.py
ruterstop/tests/__init__.py
ruterstop/tests/test_cli.py
ruterstop/tests/test_data.json
ruterstop/tests/test_ruterstop.py
ruterstop/tests/test_stop_data.json
ruterstop/tests/test_utils.py
ruterstop/tests/test_webapp.py
ruterstop/utils.py
ruterstop-0.5.1.dist-info/entry_points.txt
ruterstop-0.5.1.dist-info/LICENSE
ruterstop-0.5.1.dist-info/WHEEL
ruterstop-0.5.1.dist-info/METADATA
ruterstop-0.5.1.dist-info/RECORD
