Metadata-Version: 2.1
Name: ruterstop
Version: 0.5.1
Summary: Et program som viser sanntidsinformasjon for stoppesteder i Oslo og deler av Viken.
Home-page: https://github.com/stigok/ruterstop
License: MIT
Keywords: ruter,entur,ruter-api,kollektivtransport,oslo
Author: Stig Otnes Kolstad
Author-email: stig@stigok.com
Requires-Python: >=3.6,<4.0
Classifier: License :: OSI Approved :: MIT License
Classifier: Programming Language :: Python :: 3
Classifier: Programming Language :: Python :: 3 :: Only
Classifier: Programming Language :: Python :: 3.6
Classifier: Programming Language :: Python :: 3.7
Classifier: Programming Language :: Python :: 3.8
Classifier: Programming Language :: Python :: 3.9
Requires-Dist: bottle (>=0.12.19,<0.13.0)
Requires-Dist: requests (>=2.25.1,<3.0.0)
Requires-Dist: toml (>=0.10.2,<0.11.0)
Project-URL: Documentation, http://github.com/stigok/ruterstop
Project-URL: Repository, https://github.com/stigok/ruterstop
